Verilog/CLA.v
// 4-Bit Carry Look-Ahead Adder
module CLA (a,b,Cin,sum,carry);

    // Inputs
    input [3:0] a;
    input [3:0] b;
    input Cin;

    //Outputs
    output [3:0] sum;
    output [3:0] carry;

    //Intermediates
    //Propagate
    wire [3:0] p;
    //Generate
    wire [3:0] g;
    wire w1,w2,w3,w4;

    //Generate g_i = a_i AND b_i
    and GEN0(g[0],a[0],b[0]); 
    and GEN1(g[1],a[1],b[1]);
    and GEN2(g[2],a[2],b[2]); 
    and GEN3(g[3],a[3],b[3]);

    //Propagate p_i = a_i XOR b_i
    xor PROP0(p[0],a[0],b[0]);
    xor PROP1(p[1],a[1],b[1]);
    xor PROP2(p[2],a[2],b[2]);
    xor PROP3(p[3],a[3],b[3]);

    //Carry carry_{i+1} = (p_i AND c_i) OR g_i
    and AND0(w0,p[0],Cin);
    or OR0(carry[0],w0,g[0]);

    and AND11(w11,p[1],p[0],Cin);
    and AND12(w12,p[1],g[0]);
    or OR1(carry[1],w11,w12,g[1]);
    //and AND1(w2,p[1],carry[0]);
    //or OR1(carry[1],w2,g[1]);

    and AND21(w21,p[2],p[1],p[0],Cin);
    and AND22(w22,p[2],p[1],g[0]);
    and AND23(w23,p[2],g[1]);
    or OR2(carry[2],w21,w22,w23,g[2]);
    //and AND2(w3,p[2],carry[1]);
    //or OR2(carry[2],w3,g[2]);

    and AND31(w31,p[3],p[2],p[1],p[0],Cin);
    and AND32(w32,p[3],p[2],p[1],g[0]);
    and AND33(w33,p[3],p[2],g[1]);
    and AND34(w34,p[3],g[2]);
    or OR3(carry[3],w31,w32,w33,w34,g[3]);
    //and AND3(w4,p[3],carry[2]);
    //or OR3(Cout,w4,g[3]);

    //Sum sum_i = p_i XOR carry_i   
    xor SUM0(sum[0],p[0],Cin);
    xor SUM1(sum[1],p[1],carry[0]);
    xor SUM2(sum[2],p[2],carry[1]);
    xor SUM3(sum[3],p[3],carry[2]);

endmodule

Verilog/CLA_testbench.v
`timescale 1ns/1ps
module CLA_testbench();
    reg [3:0] a;
    reg [3:0] b;
    reg Cin;

    output [3:0] sum;
    output [3:0] carry;

    CLA abc(.a(a),.b(b),.Cin(Cin),.sum(sum),.carry(carry));

    initial begin

	    $dumpfile("CLA.vcd");
     	$dumpvars(0,CLA_testbench);

        a = 0;
        b = 0;
        Cin = 0;
	    #10 a = 4'd6; b = 4'd2;
	    $monitor( "a = %b, b = %b , Cin = %b , carry[3] = %b, sum = %b",a,b,Cin,carry[3],sum);
        #20 a = 4'd3; b = 4'd10;
        $monitor( "a = %d, b = %d , Cin = %b , carry[3] = %b, sum = %d",a,b,Cin,carry[3],sum);
        #20 a = 4'd11; b = 4'd10; Cin = 1;
        $monitor( "a = %d, b = %d , Cin = %b , carry[3] = %b, sum = %d",a,b,Cin,carry[3],sum);
        #20 a = 4'd0; b = 4'd0; Cin = 0;
        $monitor( "a = %d, b = %d , Cin = %b , carry[3] = %b, sum = %d",a,b,Cin,carry[3],sum);
        #20 a = 4'd9; b = 4'd0; Cin = 1;
        $monitor( "a = %d, b = %d , Cin = %b , carry[3] = %b, sum = %d",a,b,Cin,carry[3],sum);
        #20 a = 4'd15; b = 4'd15; Cin = 1;
        $monitor( "a = %d, b = %d , Cin = %b , carry[3] = %b, sum = %d",a,b,Cin,carry[3],sum);
        #20 a = 4'd6; b = 4'd2; Cin = 0;
        $monitor( "a = %d, b = %d , Cin = %b , carry[3] = %b, sum = %d",a,b,Cin,carry[3],sum);
        #20;
        $finish;

    end
endmodule

Verilog/CLA.vcd
$date
	Mon Dec  6 15:21:43 2021
$end
$version
	Icarus Verilog
$end
$timescale
	1ps
$end
$scope module CLA_testbench $end
$var wire 4 ! sum [3:0] $end
$var wire 4 " carry [3:0] $end
$var reg 1 # Cin $end
$var reg 4 $ a [3:0] $end
$var reg 4 % b [3:0] $end
$scope module abc $end
$var wire 1 # Cin $end
$var wire 4 & a [3:0] $end
$var wire 4 ' b [3:0] $end
$var wire 1 ( w0 $end
$var wire 1 ) w11 $end
$var wire 1 * w12 $end
$var wire 1 + w21 $end
$var wire 1 , w22 $end
$var wire 1 - w23 $end
$var wire 1 . w31 $end
$var wire 1 / w32 $end
$var wire 1 0 w33 $end
$var wire 1 1 w34 $end
$var wire 4 2 sum [3:0] $end
$var wire 4 3 p [3:0] $end
$var wire 4 4 g [3:0] $end
$var wire 4 5 carry [3:0] $end
$upscope $end
$upscope $end
$enddefinitions $end
#0
$dumpvars
b0 5
b0 4
b0 3
b0 2
01
00
0/
0.
0-
0,
0+
0*
0)
0(
b0 '
b0 &
b0 %
b0 $
0#
b0 "
b0 !
$end
#10000
b110 "
b110 5
1-
b1000 !
b1000 2
b10 4
b100 3
b10 %
b10 '
b110 $
b110 &
#30000
b10 "
b10 5
0-
b1101 !
b1101 2
b1001 3
b1010 %
b1010 '
b11 $
b11 &
#50000
b1011 "
b1011 5
b1010 4
b1 3
1(
b110 !
b110 2
1#
b1011 $
b1011 &
#70000
b0 "
b0 5
b0 4
b0 3
0(
b0 !
b0 2
0#
b0 %
b0 '
b0 $
b0 &
#90000
b1 "
b1 5
1(
b1001 3
b1010 !
b1010 2
1#
b1001 $
b1001 &
#110000
0(
b1111 !
b1111 2
b1111 "
b1111 5
b0 3
b1111 4
b1111 %
b1111 '
b1111 $
b1111 &
#130000
1-
b110 "
b110 5
b100 3
b10 4
b1000 !
b1000 2
0#
b10 %
b10 '
b110 $
b110 &
